LICENSE.txt
MANIFEST.in
README.md
setup.py
symath/__init__.py
symath/calculus.py
symath/core.py
symath/factor.py
symath/functions.py
symath/isymath.py
symath/match.py
symath/memoize.py
symath/simplestruct.py
symath/simplify.py
symath/stdops.py
symath/util.py
symath.egg-info/PKG-INFO
symath.egg-info/SOURCES.txt
symath.egg-info/dependency_links.txt
symath.egg-info/not-zip-safe
symath.egg-info/pbr.json
symath.egg-info/requires.txt
symath.egg-info/top_level.txt
symath/algorithms/__init__.py
symath/algorithms/editdistance.py
symath/datastructures/__init__.py
symath/datastructures/onetimequeue.py
symath/graph/__init__.py
symath/graph/algorithms.py
symath/graph/directed.py
symath/graph/generation.py
symath/graph/signatures.py
symath/graph/simplify.py
symath/solvers/__init__.py
symath/solvers/msz3.py