Metadata-Version: 1.1
Name: symath
Version: 0.1.23
Summary: symbolic mathematics for python
Home-page: http://github.com/bniemczyk/symbolic
Author: Brandon Niemczyk
Author-email: brandon.niemczyk@gmail.com
License: BSD
Platform: UNKNOWN
Classifier: Development Status :: 3 - Alpha
Classifier: Intended Audience :: Developers
Classifier: Intended Audience :: Science/Research
Classifier: License :: OSI Approved :: BSD License
Classifier: Topic :: Scientific/Engineering :: Mathematics
